barmoury/__init__.py
barmoury/globals.py
barmoury/api/__init__.py
barmoury/api/config/__init__.py
barmoury/api/config/error_adviser.py
barmoury/api/config/iroute.py
barmoury/api/config/jwt_manager.py
barmoury/api/config/request_auditor_adapter.py
barmoury/api/config/route.py
barmoury/api/config/route_validator.py
barmoury/api/config/setup.py
barmoury/api/controller/__init__.py
barmoury/api/controller/controller.py
barmoury/api/decorator/__init__.py
barmoury/api/decorator/entity.py
barmoury/api/decorator/jwt_open_route.py
barmoury/api/decorator/request_mapping.py
barmoury/api/decorator/route_validator_open.py
barmoury/api/decorator/secured.py
barmoury/api/enum/__init__.py
barmoury/api/enum/request_method.py
barmoury/api/exception/__init__.py
barmoury/api/exception/access_denied_exception.py
barmoury/api/exception/class_unexpected_exception.py
barmoury/api/exception/constraint_validation_exception.py
barmoury/api/exception/entity_not_found_exception.py
barmoury/api/exception/invalid_argument_exception.py
barmoury/api/exception/method_signature_exception.py
barmoury/api/exception/missing_required_parameter_exception.py
barmoury/api/exception/missing_token_exception.py
barmoury/api/exception/route_not_supported_exception.py
barmoury/api/exception/route_validator_exception.py
barmoury/api/exception/validation_exception.py
barmoury/api/model/__init__.py
barmoury/api/model/api_response.py
barmoury/api/model/model.py
barmoury/api/model/user_details.py
barmoury/api/timeo/__init__.py
barmoury/audit/__init__.py
barmoury/audit/audit.py
barmoury/audit/auditor.py
barmoury/cache/__init__.py
barmoury/cache/cache.py
barmoury/cache/list_cache_impl.py
barmoury/copier/__init__.py
barmoury/copier/copier.py
barmoury/copier/copy_property.py
barmoury/crypto/__init__.py
barmoury/crypto/encryptor.py
barmoury/crypto/zlib_compressor.py
barmoury/eloquent/__init__.py
barmoury/eloquent/query_armoury.py
barmoury/eloquent/request_param_filter.py
barmoury/log/__init__.py
barmoury/log/log.py
barmoury-1.0.41.dist-info/licenses/LICENSE
barmoury-1.0.41.dist-info/METADATA
barmoury-1.0.41.dist-info/WHEEL
barmoury-1.0.41.dist-info/top_level.txt
barmoury-1.0.41.dist-info/RECORD
