Metadata-Version: 2.4
Name: barmoury
Version: 1.0.41
Summary: The super Backend Toolkit 🔨 🔧 🚀
Author-email: Adewale Azeez <iamthecarisma@gmail.com>
License: MIT License
Project-URL: Homepage, https://barmoury.github.io
Project-URL: Source, https://github.com/barmoury/barmoury-python
Project-URL: Issues, https://github.com/barmoury/barmoury-python/issues
Keywords: barmoury,api,orm,peewee,starlette,fastify,django,thecarisma
Classifier: Development Status :: 3 - Alpha
Classifier: Intended Audience :: Developers
Classifier: Operating System :: OS Independent
Classifier: Programming Language :: Python :: 3
Classifier: Topic :: Internet :: WWW/HTTP :: WSGI
Classifier: License :: OSI Approved :: MIT License
Requires-Python: >=3.12
License-File: LICENSE
Requires-Dist: pyjwt
Requires-Dist: peewee
Requires-Dist: starlette
Requires-Dist: jsonschema
Requires-Dist: httpagentparser
Dynamic: license-file
